LICENSE.txt
MANIFEST.in
README.md
setup.cfg
setup.py
django_treewidget.egg-info/PKG-INFO
django_treewidget.egg-info/SOURCES.txt
django_treewidget.egg-info/dependency_links.txt
django_treewidget.egg-info/top_level.txt
treewidget/__init__.py
treewidget/apps.py
treewidget/fields.py
treewidget/formatters.py
treewidget/tests.py
treewidget/tree.py
treewidget/urls.py
treewidget/views.py
treewidget/static/treewidget/default.css
treewidget/static/treewidget/default.js
treewidget/static/treewidget/jstree.js
treewidget/static/treewidget/jstree.min.js
treewidget/static/treewidget/themes/default/32px.png
treewidget/static/treewidget/themes/default/40px.png
treewidget/static/treewidget/themes/default/style.css
treewidget/static/treewidget/themes/default/style.min.css
treewidget/static/treewidget/themes/default/throbber.gif
treewidget/static/treewidget/themes/default-dark/32px.png
treewidget/static/treewidget/themes/default-dark/40px.png
treewidget/static/treewidget/themes/default-dark/style.css
treewidget/static/treewidget/themes/default-dark/style.min.css
treewidget/static/treewidget/themes/default-dark/throbber.gif
treewidget/templates/treewidget/treebuttons.html
treewidget/templates/treewidget/treewidget.html