Metadata-Version: 2.1
Name: django-treewidget
Version: 0.4.4
Summary: treewidget for django admin
Home-page: https://github.com/jerch/django-treewidget
Author: Joerg Breitbart
Author-email: j.breitbart@netzkolchose.de
License: MIT
Download-URL: https://github.com/jerch/django-treewidget/archive/0.4.4.tar.gz
Keywords: django,widget,admin,tree
Platform: UNKNOWN
Classifier: Development Status :: 4 - Beta
Classifier: Intended Audience :: Developers
Classifier: Topic :: Database
Classifier: Topic :: Database :: Front-Ends
Classifier: Topic :: Software Development :: Libraries
Classifier: Framework :: Django
Classifier: Framework :: Django :: 3.2
Classifier: Framework :: Django :: 4.2
Classifier: Framework :: Django :: 5.2
Classifier: License :: OSI Approved :: MIT License
Classifier: Programming Language :: Python :: 3
Classifier: Programming Language :: Python :: 3.11
License-File: LICENSE.txt
